setup.py
pkg/__init__.py
pkg/lyr/line.lyr
pkg/lyr/point.lyr
pkg/lyr/polygon.lyr
simple_lpk.egg-info/PKG-INFO
simple_lpk.egg-info/SOURCES.txt
simple_lpk.egg-info/dependency_links.txt
simple_lpk.egg-info/entry_points.txt
simple_lpk.egg-info/requires.txt
simple_lpk.egg-info/top_level.txt