Metadata-Version: 1.0
Name: simple-lpk
Version: 0.0.5
Summary: Simple tool for creating an ArcGIS layer package from a shapefile
Home-page: https://github.com/databasin/simple-lpk
Author: databasin
Author-email: databasinadmin@consbio.org
License: see LICENSE
Platform: UNKNOWN
